zos_utilities/__init__.py
zos_utilities/cpc.py
zos_utilities/dasd_volume.py
zos_utilities/data_set.py
zos_utilities/julian_to_datetime.py
zos_utilities/logical_cpu.py
zos_utilities/lpar.py
zos_utilities-0.6.1.dist-info/AUTHORS.rst
zos_utilities-0.6.1.dist-info/LICENSE
zos_utilities-0.6.1.dist-info/METADATA
zos_utilities-0.6.1.dist-info/WHEEL
zos_utilities-0.6.1.dist-info/top_level.txt
zos_utilities-0.6.1.dist-info/RECORD
