Metadata-Version: 2.1
Name: zos-utilities
Version: 0.6.1
Summary: Library for performing various utility functions for z/OS
Home-page: https://github.com/Tam-Lin/zos-utilities
Author: Kevin McKenzie
Author-email: kmckenzi@us.ibm.com
License: Apache Software License 2.0
Keywords: zos-utilities
Classifier: Development Status :: 2 - Pre-Alpha
Classifier: Intended Audience :: Developers
Classifier: License :: OSI Approved :: Apache Software License
Classifier: Natural Language :: English
Classifier: Programming Language :: Python :: 3
Classifier: Programming Language :: Python :: 3.7
Classifier: Programming Language :: Python :: 3.8
Classifier: Programming Language :: Python :: 3.9
Classifier: Programming Language :: Python :: 3.10
Classifier: Programming Language :: Python :: 3.11
Requires-Python: >=3.7
License-File: LICENSE
License-File: AUTHORS.rst
